quiltz/__init__.py
quiltz/domain/__init__.py
quiltz/domain/anonymizer.py
quiltz/domain/email.py
quiltz/domain/parsers.py
quiltz/domain/results.py
quiltz/domain/validator.py
quiltz/domain/version.py
quiltz/domain/id/__init__.py
quiltz/domain/id/id.py
quiltz/domain/id/testbuilders.py
quiltz_domain-0.8.1.dist-info/LICENSE
quiltz_domain-0.8.1.dist-info/METADATA
quiltz_domain-0.8.1.dist-info/WHEEL
quiltz_domain-0.8.1.dist-info/top_level.txt
quiltz_domain-0.8.1.dist-info/RECORD
