Metadata-Version: 2.1
Name: quiltz-domain
Version: 0.8.1
Summary: A domain utility module for python
Home-page: https://github.com/qwaneu/quiltz-domain
Author: Rob Westgeest
Author-email: rob@qwan.eu
Classifier: Programming Language :: Python :: 3
Classifier: License :: OSI Approved :: MIT License
Classifier: Operating System :: OS Independent
License-File: LICENSE
